about/__init__.py
about/admin.py
about/apps.py
about/static/css/about/bethany_ds.css
about/static/css/about/medicio_ds.css
about/static/css/about/medilab_ds.css
about/static/css/about/mentor_ds.css
about/templates/about/_common.html
about/templates/about/bethany_ds.html
about/templates/about/medicio_ds.html
about/templates/about/medilab_ds.html
about/templates/about/mentor_ds.html
about/templatetags/__init__.py
about/templatetags/about_tags.py
django_about_ds-0.1.0.dist-info/LICENSE
django_about_ds-0.1.0.dist-info/METADATA
django_about_ds-0.1.0.dist-info/WHEEL
django_about_ds-0.1.0.dist-info/top_level.txt
django_about_ds-0.1.0.dist-info/RECORD
